rhdndat/__init__.py
rhdndat/__main__.py
rhdndat-2.7.0.dist-info/entry_points.txt
rhdndat-2.7.0.dist-info/LICENSE.txt
rhdndat-2.7.0.dist-info/WHEEL
rhdndat-2.7.0.dist-info/METADATA
rhdndat-2.7.0.dist-info/RECORD
