Metadata-Version: 2.1
Name: rhdndat
Version: 2.7.0
Summary: www.romhacking.net update checker
Home-page: https://github.com/i30817/rhdndat
License: GNU General Public License v3.0
Author: i30817
Author-email: i30817@gmail.com
Requires-Python: >=3.8,<4.0
Classifier: License :: Other/Proprietary License
Classifier: Programming Language :: Python :: 3
Classifier: Programming Language :: Python :: 3.10
Classifier: Programming Language :: Python :: 3.8
Classifier: Programming Language :: Python :: 3.9
Requires-Dist: beautifulsoup4 (>=4.10.0,<5.0.0)
Requires-Dist: colorama (>=0.4.4,<0.5.0)
Requires-Dist: lxml (>=4.9.1,<5.0.0)
Requires-Dist: questionary (>=1.10.0,<2.0.0)
Requires-Dist: requests (>=2.31.0,<3.0.0)
Requires-Dist: typer (>=0.9.0,<0.10.0)
Requires-Dist: xattr (>=0.9.9,<0.10.0); sys_platform != "win32"
Project-URL: Bug Tracker, https://github.com/i30817/rhdndat/issues
Project-URL: Repository, https://github.com/i30817/rhdndat
Project-URL: documentation, https://github.com/i30817/rhdndat#readme
Project-URL: homepage, https://github.com/i30817/rhdndat
